nnue_trainer/__init__.py
nnue_trainer/cli.py
nnue_trainer/data.py
nnue_trainer/nnue.py
nnue_trainer/quantization.py
nnue_trainer/trainer.py
nnue_trainer-0.1.1.dist-info/METADATA
nnue_trainer-0.1.1.dist-info/WHEEL
nnue_trainer-0.1.1.dist-info/entry_points.txt
nnue_trainer-0.1.1.dist-info/top_level.txt
nnue_trainer-0.1.1.dist-info/RECORD
